stream_unzip.libs/libgcc_s-a04fdf82.so.1
stream_unzip-0.0.99.dist-info/RECORD
stream_unzip-0.0.99.dist-info/METADATA
stream_unzip-0.0.99.dist-info/WHEEL
stream_unzip-0.0.99.dist-info/licenses/LICENSE
stream_unzip/__init__.py
stream_unzip/_zipcrypto.cpython-37m-x86_64-linux-gnu.so
stream_unzip/py.typed
