Metadata-Version: 2.3
Name: stream-unzip
Version: 0.0.99
Classifier: Programming Language :: Python :: 3
Classifier: License :: OSI Approved :: MIT License
Classifier: Topic :: System :: Archiving :: Compression
Classifier: Typing :: Typed
Requires-Dist: pycryptodome >=3.10.1
Requires-Dist: stream-inflate >=0.0.12
Requires-Dist: coverage >=6.2 ; extra == 'dev'
Requires-Dist: mypy >=1.4.1 ; extra == 'dev'
Requires-Dist: pytest >=6.2.5 ; extra == 'dev'
Requires-Dist: pytest-cov >=3.0.0 ; extra == 'dev'
Requires-Dist: trio >=0.19.0 ; extra == 'dev'
Requires-Dist: mypy ==1.4.1 ; extra == 'ci'
Requires-Dist: pycryptodome ==3.10.1 ; extra == 'ci'
Requires-Dist: stream-inflate ==0.0.12 ; extra == 'ci'
Provides-Extra: dev
Provides-Extra: ci
License-File: LICENSE
Summary: Python function to stream unzip all the files in a ZIP archive, without loading the entire ZIP file into memory or any of its uncompressed files
Author-email: Department for International Trade <sre@digital.trade.gov.uk>
Requires-Python: >=3.7.1
Project-URL: Documentation, https://stream-unzip.docs.trade.gov.uk/
Project-URL: Source, https://github.com/uktrade/stream-unzip
